gam_g4-0.5.0.dist-info/RECORD
gam_g4-0.5.0.dist-info/WHEEL
gam_g4-0.5.0.dist-info/top_level.txt
gam_g4-0.5.0.dist-info/METADATA
gam_g4/qt5Setup.py
gam_g4/__init__.py
gam_g4/g4DataSetup.py
gam_g4/gam_g4.cpython-39-darwin.so
gam_g4/plugins/platforms/libqoffscreen.dylib
gam_g4/plugins/platforms/libqminimal.dylib
gam_g4/plugins/platforms/libqcocoa.dylib
gam_g4/plugins/imageformats/libqgif.dylib
gam_g4/plugins/imageformats/libqwbmp.dylib
gam_g4/plugins/imageformats/libqwebp.dylib
gam_g4/plugins/imageformats/libqico.dylib
gam_g4/plugins/imageformats/libqjpeg.dylib
gam_g4/plugins/imageformats/libqtiff.dylib
gam_g4/plugins/imageformats/libqsvg.dylib
gam_g4/plugins/imageformats/libqicns.dylib
gam_g4/plugins/imageformats/libqtga.dylib
gam_g4/plugins/imageformats/libqmacjp2.dylib
gam_g4/plugins/miniconda/libQt5Svg.5.9.7.dylib
gam_g4/gam_lib/__init__.py
gam_g4/.dylibs/libG4clhep.dylib
gam_g4/.dylibs/libicudata.58.2.dylib
gam_g4/.dylibs/libQt5Widgets.5.9.7.dylib
gam_g4/.dylibs/libG4GMocren.dylib
gam_g4/.dylibs/libxcb.1.dylib
gam_g4/.dylibs/libG4ptl.0.0.2.dylib
gam_g4/.dylibs/libG4geometry.dylib
gam_g4/.dylibs/libG4processes.dylib
gam_g4/.dylibs/libG4tools.dylib
gam_g4/.dylibs/libfftw3f_threads.3.dylib
gam_g4/.dylibs/libicuuc.58.2.dylib
gam_g4/.dylibs/libG4persistency.dylib
gam_g4/.dylibs/libG4intercoms.dylib
gam_g4/.dylibs/libG4parmodels.dylib
gam_g4/.dylibs/libXt.6.dylib
gam_g4/.dylibs/libG4error_propagation.dylib
gam_g4/.dylibs/libG4gl2ps.dylib
gam_g4/.dylibs/libG4tracking.dylib
gam_g4/.dylibs/libG4analysis.dylib
gam_g4/.dylibs/libQt5OpenGL.5.9.7.dylib
gam_g4/.dylibs/libG4OpenGL.dylib
gam_g4/.dylibs/libICE.6.dylib
gam_g4/.dylibs/libG4digits_hits.dylib
gam_g4/.dylibs/libG4physicslists.dylib
gam_g4/.dylibs/libX11.6.dylib
gam_g4/.dylibs/libpng16.16.dylib
gam_g4/.dylibs/libG4tasking.dylib
gam_g4/.dylibs/libc++.1.0.dylib
gam_g4/.dylibs/libG4interfaces.dylib
gam_g4/.dylibs/libQt5PrintSupport.5.9.7.dylib
gam_g4/.dylibs/libglapi.0.dylib
gam_g4/.dylibs/libz.1.2.12.dylib
gam_g4/.dylibs/libG4visHepRep.dylib
gam_g4/.dylibs/libG4zlib.dylib
