Metadata-Version: 2.1
Name: gam-g4
Version: 0.5.0
Summary: Simulation for Medical Physics
Home-page: https://github.com/dsarrut/gam-gate
Author: Opengate collaboration
Author-email: david.sarrut@creatis.insa-lyon.fr
Classifier: Programming Language :: Python :: 3
Classifier: License :: OSI Approved :: Apache Software License
Classifier: Operating System :: OS Independent
Requires-Python: >=3.5
Requires-Dist: wget
Requires-Dist: colored
